aily_cli/__init__.py
aily_cli/cli.py
aily_cli-0.0.1.dist-info/METADATA
aily_cli-0.0.1.dist-info/WHEEL
aily_cli-0.0.1.dist-info/entry_points.txt
aily_cli-0.0.1.dist-info/top_level.txt
aily_cli-0.0.1.dist-info/RECORD
