Metadata-Version: 2.1
Name: aily-cli
Version: 0.0.1
Summary: Aily CLI
Home-page: https://aily.pro
Author: stao
Author-email: werewolf_st@hotmail.com
Classifier: Programming Language :: Python :: 3
Requires-Dist: click
